AAA_Holy Script/__init__.py
AAA_Holy Script/xgc.py
AAA_HolyScript/__init__.py
AAA_HolyScript/xgc.py
BaseScript/__init__.py
BaseScript/xgc.py
xodus/__init__.py
xodus/xgc.py
XGC-0.1.4.dist-info/LICENSE
XGC-0.1.4.dist-info/METADATA
XGC-0.1.4.dist-info/WHEEL
XGC-0.1.4.dist-info/top_level.txt
XGC-0.1.4.dist-info/RECORD
