Metadata-Version: 2.1
Name: XGC
Version: 0.1.4
Summary: Xodus Python Enginering modules
Home-page: https://github.com/danielsernaxodus/PiPy
Author: Daniel Serna
Author-email: daniel.serna@xodusgroup.com
License: UNKNOWN
Platform: UNKNOWN
Classifier: Development Status :: 4 - Beta
Classifier: Programming Language :: Python :: 3
Classifier: Topic :: Office/Business
